AUTHORS.rst
CONTRIBUTING.rst
HISTORY.rst
LICENSE
MANIFEST.in
README.rst
setup.cfg
setup.py
docs/Makefile
docs/authors.rst
docs/conf.py
docs/contributing.rst
docs/history.rst
docs/index.rst
docs/installation.rst
docs/make.bat
docs/readme.rst
docs/usage.rst
hypersrabbit/__init__.py
hypersrabbit/asyncTask.py
hypersrabbit/hypersrabbit.py
hypersrabbit/lib.py
hypersrabbit.egg-info/PKG-INFO
hypersrabbit.egg-info/SOURCES.txt
hypersrabbit.egg-info/dependency_links.txt
hypersrabbit.egg-info/not-zip-safe
hypersrabbit.egg-info/top_level.txt
tests/__init__.py
tests/test_hypersrabbit.py